urp/__init__.py
urp/client.py
urp/common.py
urp/framework.py
urp/server.py
unnamed_rpc-0.0.1.dist-info/WHEEL
unnamed_rpc-0.0.1.dist-info/METADATA
unnamed_rpc-0.0.1.dist-info/RECORD
