Metadata-Version: 2.1
Name: unnamed-rpc
Version: 0.0.1
Summary: Unnnamed PRC Protocol
Home-page: https://github.com/minecraft-podman/urp
License: LGPL-3.0-or-later
Author: Jamie Bliss
Author-email: jamie@ivyleav.es
Requires-Python: >=3.7,<4.0
Classifier: License :: OSI Approved :: GNU Lesser General Public License v3 or later (LGPLv3+)
Classifier: Programming Language :: Python :: 3
Classifier: Programming Language :: Python :: 3.7
Classifier: Programming Language :: Python :: 3.8
Requires-Dist: msgpack (>=1.0,<2.0)
Project-URL: Repository, https://github.com/minecraft-podman/urp
